MANIFEST.in
README
reprtools.py
setup.py
test_reprtool.py
reprtools.egg-info/PKG-INFO
reprtools.egg-info/SOURCES.txt
reprtools.egg-info/dependency_links.txt
reprtools.egg-info/top_level.txt