Metadata-Version: 1.0
Name: reprtools
Version: 0.1
Summary: utilities for nice object reprs
Home-page: UNKNOWN
Author: Ronny Pfannschmidt
Author-email: Ronny.Pfannschmidt@gmx.de
License: UNKNOWN
Platform: UNKNOWN
